goqueue_client/__init__.py
goqueue_client/client.py
goqueue_client/types.py
goqueue_client-1.0.0.dist-info/METADATA
goqueue_client-1.0.0.dist-info/WHEEL
goqueue_client-1.0.0.dist-info/entry_points.txt
goqueue_client-1.0.0.dist-info/license_files/LICENSE
goqueue_client-1.0.0.dist-info/RECORD
