Metadata-Version: 2.1
Name: goqueue-client
Version: 1.0.0
Summary: Official Python client for GoQueue - a high-performance distributed message queue
Project-URL: Documentation, https://abd-ulbasit.github.io/goqueue
Project-URL: Homepage, https://github.com/abd-ulbasit/goqueue
Project-URL: Issues, https://github.com/abd-ulbasit/goqueue/issues
Project-URL: Repository, https://github.com/abd-ulbasit/goqueue.git
Author-email: GoQueue Team <goqueue@example.com>
Keywords: distributed-systems,goqueue,kafka,message-broker,message-queue,pubsub,queue,rabbitmq,sqs
Classifier: Development Status :: 5 - Production/Stable
Classifier: Intended Audience :: Developers
Classifier: License :: OSI Approved :: MIT License
Classifier: Operating System :: OS Independent
Classifier: Programming Language :: Python :: 3
Classifier: Programming Language :: Python :: 3.10
Classifier: Programming Language :: Python :: 3.11
Classifier: Programming Language :: Python :: 3.12
Classifier: Programming Language :: Python :: 3.13
Classifier: Programming Language :: Python :: 3.9
Classifier: Topic :: Software Development :: Libraries :: Python Modules
Classifier: Topic :: System :: Distributed Computing
Classifier: Typing :: Typed
Requires-Python: >=3.9
Requires-Dist: httpx>=0.25.0
Provides-Extra: dev
Requires-Dist: mypy>=1.0.0; extra == 'dev'
Requires-Dist: pytest-asyncio>=0.21.0; extra == 'dev'
Requires-Dist: pytest-httpx>=0.22.0; extra == 'dev'
Requires-Dist: pytest>=7.0.0; extra == 'dev'
Requires-Dist: ruff>=0.1.0; extra == 'dev'
